jaro/__init__.py
jaro/all_tests.py
jaro/compare_jaro.py
jaro/compare_strcmp95.py
jaro/jaro.py
jaro/jaro_tests.py
jaro/strcmp95.c
jaro/strcmp95.py
jaro/typo_tables.py
jaro_winkler-2.0.3.dist-info/LICENSE
jaro_winkler-2.0.3.dist-info/METADATA
jaro_winkler-2.0.3.dist-info/WHEEL
jaro_winkler-2.0.3.dist-info/top_level.txt
jaro_winkler-2.0.3.dist-info/RECORD
